fluxbuild/__init__.py
fluxbuild-0.0.1.dist-info/LICENSE
fluxbuild-0.0.1.dist-info/METADATA
fluxbuild-0.0.1.dist-info/WHEEL
fluxbuild-0.0.1.dist-info/RECORD
